Workbook
Name ItemTotal: Schedule!$G$4254
Name MRItemTotal: Schedule!$G$4256
Name SRItemTotal: Schedule!$G$4255

Sheet Abstract
A1: ABSTRACT OF COST | F1: =Schedule!G4255 -> 12497954
A2: Name of the work : DSR - 2023 IN MS EXCEL
A4: S.H. No. | B4: Description of Sub-Head | D4: Amount (Rs)
A6: 01. | B6: Earth Work | C6: : | D6: =Schedule!G119 -> 76358
A7: 02. | B7: Concrete Work | C7: : | D7: =Schedule!G217 -> 480106
A8: 03. | B8: Reinforced Cement Concrete | C8: : | D8: =Schedule!G391 -> 839767
A9: 04. | B9: Masonry Work | C9: : | D9: =Schedule!G468 -> 390279
A10: 05. | B10: Stone Work | C10: : | D10: =Schedule!G553 -> 2195632
A11: 06. | B11: Cladding Work | C11: : | D11: =Schedule!G658 -> 454723
A12: 07. | B12: Wood and P.V.C. Work | C12: : | D12: =Schedule!G1200 -> 1941900
A13: 08. | B13: Steel Work | C13: : | D13: =Schedule!G1272 -> 56882
A14: 09. | B14: Flooring | C14: : | D14: =Schedule!G1451 -> 242519
A15: 10. | B15: Roofing | C15: : | D15: =Schedule!G1655 -> 118019
A16: 11. | B16: Finishing | C16: : | D16: =Schedule!G1885 -> 35733
A17: 12. | B17: Repairs to Buildings | C17: : | D17: =Schedule!G2024 -> 693389
A18: 13. | B18: Dismantling and Demolishing | C18: : | D18: =Schedule!G2143 -> 82595
A19: 14. | B19: Road Work | C19: : | D19: =Schedule!G2337 -> 382465
A20: 15. | B20: Sanitary Installations | C20: : | D20: =Schedule!G2677 -> 549669
A21: 16. | B21: Water Supply | C21: : | D21: =Schedule!G3505 -> 1952347
A22: 17. | B22: Drainage | C22: : | D22: =Schedule!G3684 -> 820929
A23: 18. | B23: Pile Work | C23: : | D23: =Schedule!G3747 -> 655287
A24: 19. | B24: Aluminium Work | C24: : | D24: =Schedule!G3805 -> 36680
A25: 20. | B25: Water Proofing | C25: : | D25: =Schedule!G3866 -> 54919
A26: 21. | B26: Rain Water Harvesting and Tube Well | C26: : | D26: =Schedule!G3920 -> 51686
A27: 22. | B27: Conservation of Heritage Buildings | C27: : | D27: =Schedule!G3933 -> 1886
A28: 23. | B28: Structural Glazing and Aluminium Co | C28: : | D28: =Schedule!G3948 -> 25428
A29: 24. | B29: New Technologies and Materials | C29: : | D29: =Schedule!G4252 -> 358756
B30: Total : | C30: : | D30: =SUM(D6:D29) -> 12497954 | F30: =D30-F1 -> 0
B31: Add GST @ 18.00% on (A) | C31: : | D31: =ROUND(D30*18%,0) -> 2249632
B32: Add contingencies @ 5% on (A) | C32: : | D32: =ROUND(D30*5%,0) -> 624898
B33: Grand Total | D33: =SUM(D30:D32) -> 15372484
B35: Say | D35: =ROUND((D33+30)/100,0)*100 -> 15372500
B40: Junior Telecom Officer (Civil) | C40: Sub-Divisional Engineer (Civil)
B41: BSNL Civil Sub-Division | C41: BSNL Civil Sub-Division
B42: NALGONDA | C42: NALGONDA
C48: Executive Engineer (Civil)
C49: BSNL Civil Dn-I
C50: HYDERABAD

Sheet Schedule
A1: SCHEDULE OF QUANTITIES
B2: Name of the work : DSR - 2023 IN MS EXCEL
A3: I.No. | B3: Description of Item | C3: Quantity | E3: Rate (Rs) | F3: Unit | G3: Amount(Rs)
A4: Sub-Head : Earth Work
A5: 2.1 | B5: Earth work in surface excavation not exceeding 30 cm in depth but exceeding 1.5 m in width as well as 10 sqm on plan including getting out and disposal of excavated earth upto 50 m and lift up to 1.5 m, as directed by Engineer-in-Charge: | H5: Earth work in surface excavation:
A6: 2.1.1 | B6: All kinds of soil | C6: 1 | D6: Sqm | E6: 129.85 | F6: One Square Metre | G6: =ROUND(C6*E6,0) -> 130 | H6: All kinds of soil.
A7: 2.2 | B7: Earth work by mechinical / manual means in rough excavation, banking excavated earth in layers not exceeding 20cm in depth, breaking clods, watering, rolling each layer with 'A tonne roller or wooden or steel rammers, and rolling every 3rd and top-most layer with power roller of minimum 8 tonnes and dressing up in embankments for roads, flood banks, marginal banks and guide banks or filling up ground depressions, lead upto 50 m and for all lift | H7: Earth work in rough excavation, banking excavated earth :
A8: 2.2.1 | B8: All kinds of soil | C8: 1 | D8: Cum | E8: 395.3 | F8: One Cubic Metre | G8: =ROUND(C8*E8,0) -> 395 | H8: All kinds of soil.
A9: 2.3 | B9: Banking excavated earth by mechanical / manual means in layers not exceeding 20 cm in depth, breaking clods, watering, rolling each layer with 'A tonne roller, or wooden or steel rammers, and roiling every 3rd and top-most layer with power roller of minimum 8 tonnes and dressing up, in embankments for roads, flood banks, marginal banks, and guide banks etc, lead upto 50 m and for all lift: | H9: Banking excavated earth in layers not exceeding 20 cm. in depth, breaking clods :-
A10: 2.3.1 | B10: All kinds of soil | C10: 1 | D10: Cum | E10: 197.9 | F10: One Cubic Metre | G10: =ROUND(C10*E10,0) -> 198 | H10: All kinds of soil.
A11: 2.4 | B11: Deduct for not rolling with power roller of minimum 8 tonnes for banking excavated earth in layers not exceeding 20 cm in depth. | C11: 1 | D11: Cum | E11: -5.25 | F11: One Cubic Metre | G11: =ROUND(C11*E11,0) -> -5 | H11: Deduct for not rolling with power roller.
A12: 2.5 | B12: Deduct for not watering the excavated earth for banking | C12: 1 | D12: Cum | E12: -14.25 | F12: One Cubic Metre | G12: =ROUND(C12*E12,0) -> -14 | H12: Deduct for not watering the excavated earth for banking.
A13: 2.6 | B13: Earth work in excavation by mechanical means (Hydraulic excavator) / manual means over areas (exceeding 30cm in depth, 1.5m in width as well as 10 sqm on plan) including getting out and disposal of excavated earth, lead up to 50m and lift up to 1.5m,as directed by Engineer-in-Charge. | H13: Earth work in excavation over areas :-
A14: 2.6.1 | B14: All kinds of soil | C14: 1 | D14: Cum | E14: 177.5 | F14: One Cubic Metre | G14: =ROUND(C14*E14,0) -> 178 | H14: All kinds of soil .
A15: 2.7 | B15: Earth work in excavation by mechanical means (Hydraulic excavator) / manual means over areas (exceeding 30 cm in depth, 1.5m in width as well as 10 sqm on plan) including getting out and disposal of excavated earth, lead up to 50 m and lift up to 1.5m, as directed by Engineer-in-Charge. | H15: Earth work in excavation over areas :-
A16: 2.7.1 | B16: Ordinary rock | C16: 1 | D16: Cum | E16: 498.9 | F16: One Cubic Metre | G16: =ROUND(C16*E16,0) -> 499 | H16: Ordinary rock.
A17: 2.7.2 | B17: Hard rock (requiring blasting) | C17: 1 | D17: Cum | E17: 874.4 | F17: One Cubic Metre | G17: =ROUND(C17*E17,0) -> 874 | H17: Hard rock (requ blasting).
A18: 2.7.3 | B18: Hard rock (blasting prohibited) | C18: 1 | D18: Cum | E18: 1432.95 | F18: One Cubic Metre | G18: =ROUND(C18*E18,0) -> 1433 | H18: Hard rock (blasting prohi).
A19: 2.8 | B19: Earth work in excavation by mechanical means (Hydraulic excavator) / manual means in foundation trenches or drains (not exceeding 1.5 m in width or 10 sqm on plan) including dressing of sides and ramming of bottoms, lift up to 1.5 m, including getting out the excavated soil and disposal of surplus excavated soil as directed, within a lead of 50 m. | H19: E/W in excavation in foundation trenches :-
A20: 2.8.1 | B20: All kinds of soil. | C20: 1 | D20: Cum | E20: 260.3 | F20: One Cubic Metre | G20: =ROUND(C20*E20,0) -> 260 | H20: All kinds of soil.
A21: 2.9 | B21: Excavation work by mechanical means (Hydraulic excavator)/ manual means in foundation trenches or drains (not exceeding 1.5m in width or 10 sqm on plan) including dressing of sides and ramming of bottoms, lift up to 1.5 m, including getting out the excavated soil and disposal of surplus excavated soils as directed, within a lead of 50m. | H21: Excavation work in foundation, trenches :-
A22: 2.9.1 | B22: Ordinary rock | C22: 1 | D22: Cum | E22: 632.95 | F22: One Cubic Metre | G22: =ROUND(C22*E22,0) -> 633 | H22: Ordinary rock.
A23: 2.9.2 | B23: Hard rock (requiring blasting) | C23: 1 | D23: Cum | E23: 1049.8 | F23: One Cubic Metre | G23: =ROUND(C23*E23,0) -> 1050 | H23: Hard rock (requ blasting).
A24: 2.9.3 | B24: Hard rock (blasting prohibited) | C24: 1 | D24: Cum | E24: 1523.05 | F24: One Cubic Metre | G24: =ROUND(C24*E24,0) -> 1523 | H24: Hard rock (blasting probi).
A25: 2.10 | B25: Excavating trenches of required width for pipes, cables, etc including excavation for sockets, and dressing of sides, ramming of bottoms, depth up to 1.5 m, including getting out the excavated soil, and then returning the soil as required, in layers not exceeding 20 cm in depth, including consolidating each deposited layer by ramming, watering, etc. and disposing of surplus excavated soil as directed, within a lead of 50 m : | H25: Excavating trenches for pipes , cables
A26: 2.10.1 | B26: All kinds of soil | H26: All kinds of soil
A27: 2.10.1.1 | B27: Pipes, cables etc, not exceeding 80 mm dia. | C27: 1 | D27: Nos | E27: 215.6 | F27: One Metre | G27: =ROUND(C27*E27,0) -> 216 | H27: Pipes upto 80 mm dia.
A28: 2.10.1.2 | B28: Pipes, cables etc. exceeding 80 mm dia. but not exceeding 300 mm dia | C28: 1 | D28: Nos | E28: 352.15 | F28: One Metre | G28: =ROUND(C28*E28,0) -> 352 | H28: Pipes, cables etc. exceeding 80 mm dia. but not exceeding 300 mm dia
A29: 2.10.1.3 | B29: Pipes, cables etc. exceeding 300 mm dia but not exceeding 600 mm. | C29: 1 | D29: Nos | E29: 549.75 | F29: One Metre | G29: =ROUND(C29*E29,0) -> 550 | H29: Pipes , cables 300 to 600 mm.
A30: 2.13 | B30: Excavating trenches of required width for pipes, cables, etc, including excavation for sockets, depth up to 1.5 m, including getting out the excavated materials, returning the soil as required in layers not exceeding 20 cm in depth, including consolidating each deposited layers by ramming, watering etc., stacking serviceable material for measurements and disposal of unserviceable material as directed, within a lead of 50m : | H30: Excavating trenches for pipes cables
A31: 2.13.1 | B31: Ordinary rock : | H31: Ordinary rocks :
A32: 2.13.1.1 | B32: Pipes, cables etc. not exceeding 80 mm dia. | C32: 1 | D32: Nos | E32: 403.3 | F32: One Metre | G32: =ROUND(C32*E32,0) -> 403 | H32: Pipes, upto 80 mm dia.
A33: 2.13.1.2 | B33: Pipes, cables etc. exceeding 80 mm dia but not exceeding 300 mm dia. | C33: 1 | D33: Nos | E33: 998.65 | F33: One Metre | G33: =ROUND(C33*E33,0) -> 999 | H33: Pipes, 80 mm to 300 mm dia.
A34: 2.13.1.3 | B34: Pipes, cables exceeding 300 mm dia but not exceeding 600mm dia | C34: 1 | D34: Nos | E34: 1149.1 | F34: One Metre | G34: =ROUND(C34*E34,0) -> 1149 | H34: Pipes 300 to 600 mm. dia
A35: 2.13.2 | B35: Hard rock (requiring blasting) | H35: Hard rock (requi blasting) :
A36: 2.13.2.1 | B36: Pipes, cables etc. not exceeding 80 mm dia. | C36: 1 | D36: Nos | E36: 603.2 | F36: One Metre | G36: =ROUND(C36*E36,0) -> 603 | H36: Pipes, upto 80 mm dia.
A37: 2.13.2.2 | B37: Pipes, cables etc. exceeding 80 mm dia. but not exceeding 300 mm dia. | C37: 1 | D37: Nos | E37: 1493.6 | F37: One Metre | G37: =ROUND(C37*E37,0) -> 1494 | H37: Pipes 80 mm to 300 mm dia.
A38: 2.13.2.3 | B38: Pipes, cables etc. exceeding 300 mm dia but not exceeding 600mm dia | C38: 1 | D38: Nos | E38: 1718.45 | F38: One Metre | G38: =ROUND(C38*E38,0) -> 1718 | H38: Pipes 300 to 600 mm.
A39: 2.13.3 | B39: Hard rock (blasting prohibited) | H39: Hard rock (blasting prohi) :
A40: 2.13.3.1 | B40: Pipes, cables etc. not exceeding 80 mm dia. | C40: 1 | D40: Nos | E40: 826.8 | F40: One Metre | G40: =ROUND(C40*E40,0) -> 827 | H40: Pipes upto 80 mm dia.
A41: 2.13.3.2 | B41: Pipes, cables etc. exceeding 80 mm dia. but not exceeding 300 mm dia. | C41: 1 | D41: Nos | E41: 2047.3 | F41: One Metre | G41: =ROUND(C41*E41,0) -> 2047 | H41: Pipes 80 mm to 300 mm dia.
A42: 2.13.3.3 | B42: Pipes, cables etc. exceeding 300 mm dia but not exceeding 600mm dia. | C42: 1 | D42: Nos | E42: 2355.75 | F42: One Metre | G42: =ROUND(C42*E42,0) -> 2356 | H42: Pipes 300 to 600 mm.
A43: 2.14 | B43: Extra for excavating trenches for pipes, cables etc. in ordinary / hard rock exceeding 1.5m in depth but not exceeding 3m.(Rate is over corresponding basic item for depth upto 1.5 metre).
A44: 2.14.1 | B44: Ordinary rock | H44: Ordinary rock
A45: 2.14.1.1 | B45: Pipes, cables etc., exceeding 80 mm dia but not exceeding 300 mm dia. | C45: 1 | D45: m | E45: 729.8 | F45: One metre | G45: =ROUND(C45*E45,0) -> 730 | H45: Pipes, cables etc., exceeding 80 mm dia but not exceeding 300 mm dia.
A46: 2.14.1.2 | B46: Pipes, cables etc., exceeding 300 mm dia but not exceeding 600 mm dia. | C46: 1 | D46: m | E46: 867.45 | F46: One metre | G46: =ROUND(C46*E46,0) -> 867 | H46: Pipes, cables etc., exceeding 300 mm dia but not exceeding 600 mm dia.
A47: 2.14.2 | B47: Hard rock | H47: Hard rock
A48: 2.14.2.1 | B48: Pipes, cables etc., exceeding 80 mm dia but not exceeding 300 mm dia. | C48: 1 | D48: m | E48: 1091.45 | F48: One metre | G48: =ROUND(C48*E48,0) -> 1091 | H48: Pipes, cables etc., exceeding 80 mm dia but not exceeding 300 mm dia.
A49: 2.14.2.2 | B49: Pipes, cables etc., exceeding 300 mm dia but not exceeding 600 mm dia. | C49: 1 | D49: m | E49: 1297.4 | F49: One metre | G49: =ROUND(C49*E49,0) -> 1297 | H49: Pipes, cables etc., exceeding 300 mm dia but not exceeding 600 mm dia.
A50: 2.14.3 | B50: Hard rock (blasting prohibited) | H50: Hard rock (blasting prohibited)
A51: 2.14.3.1 | B51: Pipes, cables etc., exceeding 80 mm dia but not exceeding 300 mm dia. | C51: 1 | D51: m | E51: 1496.1 | F51: One metre | G51: =ROUND(C51*E51,0) -> 1496 | H51: Pipes, cables etc., exceeding 80 mm dia but not exceeding 300 mm dia.
A52: 2.14.3.2 | B52: Pipes, cables etc., exceeding 300 mm dia but not exceeding 600 mm dia. | C52: 1 | D52: m | E52: 1778.15 | F52: One metre | G52: =ROUND(C52*E52,0) -> 1778 | H52: Pipes, cables etc., exceeding 300 mm dia but not exceeding 600 mm dia.
A53: 2.15 | B53: Extra for excavating trenches for pipes, cables etc. in ordinary / hard rock exceeding 3m in depth, but not exceeding 4.5m.(Rate is over corresponding basic item for depth upto 1.5 metre).
A54: 2.15.1 | B54: Ordinary rock | H54: Ordinary rock
A55: 2.15.1.1 | B55: Pipes, cables etc., exceeding 300 mm dia but not exceeding 600 mm dia. | C55: 1 | D55: m | E55: 2352.25 | F55: One metre | G55: =ROUND(C55*E55,0) -> 2352 | H55: Pipes, cables etc., exceeding 300 mm dia but not exceeding 600 mm dia.
A56: 2.16 | B56: Close timbering in trenches including strutting, shoring and packing cavities (wherever required) complete. (Measurements to be taken of the face area timbered). | H56: Close timbering in trenches :-
A57: 2.16.1 | B57: Depth not exceeding 1.5 m. | C57: 1 | D57: Sqm | E57: 139.95 | F57: One Square Metre | G57: =ROUND(C57*E57,0) -> 140 | H57: Depth not exceeding 1.5 mtr.
A58: 2.16.2 | B58: Depth exceeding 1.5 m but not exceeding 3 m. | C58: 1 | D58: Sqm | E58: 155.3 | F58: One Square Metre | G58: =ROUND(C58*E58,0) -> 155 | H58: Depth from 1.5 to 3 mtr.
A59: 2.16.3 | B59: Depth exceeding 3 m but not exceeding 4.5 m. | C59: 1 | D59: Sqm | E59: 189.65 | F59: One Square Metre | G59: =ROUND(C59*E59,0) -> 190 | H59: Depth from 3 to 4.5 mtr.
A60: 2.17 | B60: Close timbering in case of shafts, wells, cesspits, manholes and the like including strutting, shoring and packing cavities (wherever required) etc. complete.(Measurements to be taken of the face area timbered). | H60: Close timbering in case of shafts,wells,cesspits,manholes
A61: 2.17.1 | B61: Depth not exceeding 1.5 m. | C61: 1 | D61: Sqm | E61: 151.5 | F61: One Square Metre | G61: =ROUND(C61*E61,0) -> 152 | H61: Depth not exceeding 1.5 mtr.
A62: 2.17.2 | B62: Depth exceeding 1.5 m but not exceeding 3 m. | C62: 1 | D62: Sqm | E62: 184 | F62: One Square Metre | G62: =ROUND(C62*E62,0) -> 184 | H62: Depth from 3 to 4.5 mtr.
A63: 2.17.3 | B63: Depth exceeding 3 m but not exceeding 4.5 m. | C63: 1 | D63: Sqm | E63: 218.2 | F63: One Square Metre | G63: =ROUND(C63*E63,0) -> 218 | H63: Depth exceeding 3 m to 4.5 m.
A64: 2.18 | B64: Close timbering over areas including strutting, shoring and packing cavities (wherever required) etc. complete. (Measurements to be taken of the face area timbered) : | H64: Close timbering over areas :-
A65: 2.18.1 | B65: Depth not exceeding 1.5 m. | C65: 1 | D65: Sqm | E65: 125.8 | F65: One Square Metre | G65: =ROUND(C65*E65,0) -> 126 | H65: Depth not exceeding 1.5 mtr.
A66: 2.18.2 | B66: Depth exceeding 1.5 m but not exceeding 3 m. | C66: 1 | D66: Sqm | E66: 144.1 | F66: One Square Metre | G66: =ROUND(C66*E66,0) -> 144 | H66: Depth from 1.5 to 3 mtr.
A67: 2.18.3 | B67: Depth exceeding 3 m but not exceeding 4.5 m. | C67: 1 | D67: Sqm | E67: 163.15 | F67: One Square Metre | G67: =ROUND(C67*E67,0) -> 163 | H67: Depth from 3 to 4.5 mtr.
A68: 2.19 | B68: Extra for planking, strutting and packing materials for cavities (in close timbering) if required to be left permanently in position. (Face area of timber permanently left to be measured). | C68: 1 | D68: Sqm | E68: 1692.45 | F68: One Square Metre | G68: =ROUND(C68*E68,0) -> 1692 | H68: Extra for planking, strutting and packing materials for cavities (in close timbering):
A69: 2.20 | B69: Open timbering in trenches including strutting and shoring complete (measurements to be taken of the face area timbered): | H69: Open timbering in trenches
A70: 2.20.1 | B70: Depth not exceeding 1.5 m. | C70: 1 | D70: Sqm | E70: 72.05 | F70: One Square Metre | G70: =ROUND(C70*E70,0) -> 72 | H70: Depth not exceeding 1.5 m.
A71: 2.20.2 | B71: Depth exceeding 1.5 m but not exceeding 3 m. | C71: 1 | D71: Sqm | E71: 81.6 | F71: One Square Metre | G71: =ROUND(C71*E71,0) -> 82 | H71: Depth from 1.5 to 3 mtr.
A72: 2.20.3 | B72: Depth exceeding 3 m but not exceeding 4.5 m. | C72: 1 | D72: Sqm | E72: 97.25 | F72: One Square Metre | G72: =ROUND(C72*E72,0) -> 97 | H72: Depth from 3 to 4.5 mtr.
A73: 2.21 | B73: Open timbering in case of shafts, wells, cesspits, manholes and the like including strutting and shoring complete (Measurements to be taken of the face area timbered): | H73: Open timbering in case of shafts, wells, cesspits, manholes
A74: 2.21.1 | B74: Depth not exceeding 1.5 m. | C74: 1 | D74: Sqm | E74: 66.4 | F74: One Square Metre | G74: =ROUND(C74*E74,0) -> 66 | H74: Depth not exceeding 1.5 m.
A75: 2.21.2 | B75: Depth exceeding 1.5 m but not exceeding 3 m. | C75: 1 | D75: Sqm | E75: 81.65 | F75: One Square Metre | G75: =ROUND(C75*E75,0) -> 82 | H75: Depth from 1.5 to 3 mtr.
A76: 2.21.3 | B76: Depth exceeding 3 m but not exceeding 4.5 m. | C76: 1 | D76: Sqm | E76: 101.85 | F76: One Square Metre | G76: =ROUND(C76*E76,0) -> 102 | H76: Depth from 3 to 4.5 mtr.
A77: 2.22 | B77: Open timbering over areas including strutting, shoring etc. complete. (Measurements to be taken of the face area timbered): | H77: Open timbering over areas
A78: 2.22.1 | B78: Depth not exceeding 1.5 m. | C78: 1 | D78: Sqm | E78: 44.85 | F78: One Square Metre | G78: =ROUND(C78*E78,0) -> 45 | H78: Depth not exceeding 1.5 m.
A79: 2.22.2 | B79: Depth exceeding 1.5 m but not exceeding 3 m. | C79: 1 | D79: Sqm | E79: 54.95 | F79: One Square Metre | G79: =ROUND(C79*E79,0) -> 55 | H79: Depth from 1.5 to 3 mtr.
A80: 2.22.3 | B80: Depth exceeding 3 m but not exceeding 4.5 m. | C80: 1 | D80: Sqm | E80: 71.3 | F80: One Square Metre | G80: =ROUND(C80*E80,0) -> 71 | H80: Depth from 3 to 4.5 mtr.
A81: 2.23 | B81: Extra for planking and strutting in open timbering if required to be left permanently in position. (Face area of the timber permanently left to be measured). | C81: 1 | D81: Sqm | E81: 872.55 | F81: One Square Metre | G81: =ROUND(C81*E81,0) -> 873 | H81: Extra for planking and strutting in open timbering if required to be left permanently in position.
A82: 2.25 | B82: Filling available excavated earth (excluding rock) in trenches, plinth, sides of foundations etc. in layers not exceeding 20cm in depth, consolidating each deposited layer by ramming and watering, lead up to 50 m and lift up to 1.5 m. | C82: 1 | D82: Cum | E82: 196 | F82: One Cubic Metre | G82: =ROUND(C82*E82,0) -> 196 | H82: Filling available earth in trenches, plinth, side foundation etc.
A83: 2.25A | B83: Excavating, supplying and filling of local earth (including royalty) by mechanical transport up to a lead of 5 km, also including ramming and watering of the earth in layers not exceeding 20 cm in trenches, plinth, sides of foundation etc., complete. | C83: 1 | D83: Cum | E83: 700.5 | F83: One Cubic Metre | G83: =ROUND(C83*E83,0) -> 701
A84: 2.26 | B84: Extra for every additional lift of 1.5 m or part thereof in excavation /banking excavated or stacked materials. | H84: Extra for every addi lift of 1.5 m:
A85: 2.26.1 | B85: All kinds of soil. | C85: 1 | D85: Cum | E85: 126.8 | F85: One Cubic Metre | G85: =ROUND(C85*E85,0) -> 127 | H85: All kinds of soil.
A86: 2.26.2 | B86: Ordinary or hard rock. | C86: 1 | D86: Cum | E86: 227.4 | F86: One Cubic Metre | G86: =ROUND(C86*E86,0) -> 227 | H86: Ordinary or hard rock
A87: 2.27 | B87: Supplying and filling in plinth with sand under floors, including watering, ramming, consolidating and dressing complete. | C87: 1 | D87: Cum | E87: 2123.75 | F87: One Cubic Metre | G87: =ROUND(C87*E87,0) -> 2124 | H87: Suppl. and filling in plinth local sand under floor.
A88: 2.28 | B88: Surface dressing of the ground including removing vegetation and inequalities not exceeding 15 cm deep and disposal of rubbish, lead up to 50 m and lift upto1.5 m. | H88: Surface dressing of the ground not exceeding 15 cm deep
A89: 2.28.1 | B89: All kinds of soil. | C89: 1 | D89: Sqm | E89: 34.15 | F89: One Square Metre | G89: =ROUND(C89*E89,0) -> 34 | H89: All kinds of soil.
A90: 2.29 | B90: Ploughing the existing ground to a depth of 15 cm to 25 cm and watering the same. | H90: Ploughing the existing ground and watering the same.
A91: 2.29.1 | B91: All kinds of soil. | C91: 1 | D91: Sqm | E91: 34.6 | F91: One Square Metre | G91: =ROUND(C91*E91,0) -> 35 | H91: All kinds of soil.
A92: 2.30 | B92: Excavating holes more than 0.10 cum & up to 0.5 cum including getting out the excavated soil, then returning the soil as required in layers not exceeding 20 cm in depth, including consolidating each deposited layer by ramming, watering etc, disposing of surplus excavated soil, as directed within a lead of 50 m and lift upto1.5 m. | H92: Excavating holes more than 0.10 cum & up to 0.5 cum including getting out the excavated soil, then returning the soil.
A93: 2.30.1 | B93: All kinds of soil. | C93: 1 | D93: No. | E93: 82.45 | F93: Each | G93: =ROUND(C93*E93,0) -> 82 | H93: All kinds of soil.
A94: 2.30.2 | B94: Ordinary rock | C94: 1 | D94: No. | E94: 194.25 | F94: Each | G94: =ROUND(C94*E94,0) -> 194 | H94: Ordinary rock
A95: 2.30.3 | B95: Hard rock (requiring blasting) | C95: 1 | D95: No. | E95: 319.3 | F95: Each | G95: =ROUND(C95*E95,0) -> 319 | H95: Hard rock (requiring blasting)
A96: 2.30.4 | B96: Hard rock (blasting prohibited) | C96: 1 | D96: No. | E96: 461.3 | F96: Each | G96: =ROUND(C96*E96,0) -> 461 | H96: Hard rock (blasting prohibited)
A97: 2.31 | B97: Clearing jungle including uprooting of rank vegetation, grass, brush wood, trees and saplings of girth up to 30 cm measured at a height of 1 m above ground level and removal of rubbish up to a distance of 50m outside the periphery of the area cleared. | C97: 1 | D97: Sqm | E97: 17.6 | F97: One Square Metre | G97: =ROUND(C97*E97,0) -> 18 | H97: Clearing jungle i/c uprooti- ng of rank vegetation,grass, brush wood,trees etc.
A98: 2.32 | B98: Clearing grass and removal of the rubbish up to a distance of 50 m outside the periphery of the area cleared. | C98: 1 | D98: Sqm | E98: 8.95 | F98: One Square Metre | G98: =ROUND(C98*E98,0) -> 9 | H98: Clearing grass and removal of the rubbish
A99: 2.33 | B99: Felling trees of the girth (measured at a height of 1 m above ground level) including cutting of trunks and branches, removing the roots and stacking of serviceable material and disposal of unserviceable material. | H99: Felling of trees of the girth including cutting of trunks and branches
A100: 2.33.1 | B100: Beyond 30 cm girth up to and including 60 cm girth | C100: 1 | D100: No. | E100: 532.35 | F100: Each | G100: =ROUND(C100*E100,0) -> 532 | H100: Beyond 30 cm girth up to 60 cm girth
...

Sheet ReadMe
A1: DSR 2023 IN MS EXCEL WITH FORMULAS (Updated on 30.11.2023)
A2: Read Me
A3: 01. | B3: This is a estimate proforma containing all the items of CPWD published DSR-2023, generated using Jalli's App - 2023.
A4: 02. | B4: Data has been compiled and verified by many Engineers from BSNL and other Departments and from all over India (see the table below)
A5: 03. | B5: Though, the data has been verified thoroughly, this file may contain certain mistakes/omissions.
B6: Hence, the users of this file are advised to verify the correctness of the data with original DSR-2023 and Correction Slips (if any) published by CPWD.
A7: 04. | B7: Neither the author/publisher nor his associates, who compiled or verified the data for this file, are responsible for the damages/ losses whatsoever may be, that may occur directly or indirectly due to the incorrect data of this file.
A8: 05. | B8: This is not a replica of DSR-2023 published by the CPWD, but a standard Detailed Estimate Proforma which is normally used in Civil Engineering Departments of various Central / State Government or PSUs.
A9: 06. | B9: Please drop an e-mail to me at rambabujalli@gmail.com for any queries regarding this file and confine your querry to this file only.
A10: 07. | B10: This file will be updated as and when errors are noticed and the file is corrected / CS is released for DSR-2023, keep visiting our website www.jallisapp.com to download the updated version.
B12: On behalf of all , my Sincere thanks to the following Officers who compiled / verified the data for making this file!
B14: Participated in compiling the data Sri / Smt
A15: 1 | B15: Nurul Haque, Kolkata
A16: 2 | B16: Sabya sachi mitra, Kolkata
A17: 3 | B17: Vijay Prakah Sharma, Ranchi, Jharkhand.
A18: 4 | B18: CRR Varma, Hyderabad, TS
A19: 5 | B19: G.Ashok Kumar, AP
A20: 6 | B20: K.Lakshmana Babu, Visakhapatnam, AP
A21: 7 | B21: Anurag Mishra, Gorakhpur UP.
A22: 8 | B22: Nandini Moorthy, Chennai
A23: 9 | B23: Kondal Rao P, Vijayawada, AP
A24: 10 | B24: K.Senthil Velan, TN
A25: 11 | B25: Anil Jotani, Rajkot, GJ.
A26: 12 | B26: Jitendra Singh, Kolkata.
... A38: 27 | B38: Yogendra Kumar
B45: -Rambabu Jalli
B46: Hyderabad
B47: e-mail : rambabujalli@gmail.com
B48: website : | C48: www.jallisapp.com
